mate/__init__.py
mate/_version.py
mate/matchers.py
mate/testcase.py
mate/tests/__init__.py
mate/tests/test_testcase.py
mate-0.2.0.dist-info/DESCRIPTION.rst
mate-0.2.0.dist-info/METADATA
mate-0.2.0.dist-info/RECORD
mate-0.2.0.dist-info/WHEEL
mate-0.2.0.dist-info/metadata.json
mate-0.2.0.dist-info/top_level.txt
